foodsorter/__init__.py
foodsorter/sorter.py
foodsorterlib-0.1.dist-info/METADATA
foodsorterlib-0.1.dist-info/WHEEL
foodsorterlib-0.1.dist-info/top_level.txt
foodsorterlib-0.1.dist-info/RECORD
