Metadata-Version: 2.1
Name: foodsorterlib
Version: 0.1
Requires-Dist: Django
